nonebot_plugin_skland-0.6.0.dist-info/METADATA
nonebot_plugin_skland-0.6.0.dist-info/WHEEL
nonebot_plugin_skland-0.6.0.dist-info/entry_points.txt
nonebot_plugin_skland-0.6.0.dist-info/licenses/LICENSE
nonebot_plugin_skland/__init__.py
nonebot_plugin_skland/api/__init__.py
nonebot_plugin_skland/api/login.py
nonebot_plugin_skland/api/request.py
nonebot_plugin_skland/config.py
nonebot_plugin_skland/db_handler.py
nonebot_plugin_skland/download.py
nonebot_plugin_skland/exception.py
nonebot_plugin_skland/extras.py
nonebot_plugin_skland/filters.py
nonebot_plugin_skland/hook.py
nonebot_plugin_skland/migrations/02e0764f579e_fix_model_type.py
nonebot_plugin_skland/migrations/220f4e0d01fd_gacha_record.py
nonebot_plugin_skland/migrations/997049a57a3a_first_revision.py
nonebot_plugin_skland/model.py
nonebot_plugin_skland/render.py
nonebot_plugin_skland/resources/fonts/Akrobat-Bold.otf
nonebot_plugin_skland/resources/fonts/Bender-Bold.otf
nonebot_plugin_skland/resources/fonts/Bender.otf
nonebot_plugin_skland/resources/images/ark_card/assist_title.png
nonebot_plugin_skland/resources/images/ark_card/building/dorm.png
nonebot_plugin_skland/resources/images/ark_card/building/labor.png
nonebot_plugin_skland/resources/images/ark_card/building/manufact.png
nonebot_plugin_skland/resources/images/ark_card/building/meeting.png
nonebot_plugin_skland/resources/images/ark_card/building/tired.png
nonebot_plugin_skland/resources/images/ark_card/building/trading.png
nonebot_plugin_skland/resources/images/ark_card/card_img/ap.png
nonebot_plugin_skland/resources/images/ark_card/card_img/daily.png
nonebot_plugin_skland/resources/images/ark_card/card_img/hire.png
nonebot_plugin_skland/resources/images/ark_card/card_img/jade.png
nonebot_plugin_skland/resources/images/ark_card/card_img/recruit.png
nonebot_plugin_skland/resources/images/ark_card/card_img/tower.png
nonebot_plugin_skland/resources/images/ark_card/card_img/train.png
nonebot_plugin_skland/resources/images/ark_card/card_img/weekly.png
nonebot_plugin_skland/resources/images/ark_card/career/career_1.png
nonebot_plugin_skland/resources/images/ark_card/career/career_2.png
nonebot_plugin_skland/resources/images/ark_card/career/career_3.png
nonebot_plugin_skland-0.6.0.dist-info/RECORD
