Metadata-Version: 2.1
Name: nonebot-plugin-skland
Version: 0.6.0
Summary: 通过森空岛查询游戏数据
Author-Email: FrostN0v0 <1614591760@qq.com>
License: MIT
Project-URL: homepage, https://github.com/FrostN0v0/nonebot-plugin-skland
Project-URL: repository, https://github.com/FrostN0v0/nonebot-plugin-skland
Requires-Python: >=3.10
Requires-Dist: httpx>=0.27.0
Requires-Dist: nonebot-plugin-alconna>=0.57.1
Requires-Dist: nonebot-plugin-apscheduler>=0.5.0
Requires-Dist: nonebot-plugin-argot>=0.2.1
Requires-Dist: nonebot-plugin-htmlrender>=0.6.5
Requires-Dist: nonebot-plugin-localstore>=0.7.3
Requires-Dist: nonebot-plugin-orm>=0.7.6
Requires-Dist: nonebot-plugin-user>=0.5.0
Requires-Dist: nonebot2>=2.4.2
Requires-Dist: qrcode[pil]>=7.4.2
Requires-Dist: rich>=13.9.4
Requires-Dist: arclet-alconna>=1.8.38
Provides-Extra: dev
Requires-Dist: nonebot-adapter-discord>=0.1.8; extra == "dev"
Requires-Dist: nonebot-adapter-onebot>=2.4.6; extra == "dev"
Requires-Dist: nonebot-adapter-telegram>=0.1.0b20; extra == "dev"
Requires-Dist: nonebot-plugin-orm[default]>=0.7.6; extra == "dev"
Requires-Dist: nonebot2[aiohttp,fastapi]>=2.4.1; extra == "dev"
